protectsql/__init__.py
protectsql/commands.py
protectsql-0.0.8.dist-info/LICENSE
protectsql-0.0.8.dist-info/METADATA
protectsql-0.0.8.dist-info/WHEEL
protectsql-0.0.8.dist-info/entry_points.txt
protectsql-0.0.8.dist-info/top_level.txt
protectsql-0.0.8.dist-info/RECORD
