Metadata-Version: 2.1
Name: protectsql
Version: 0.0.8
Summary: A small package to track SQL injection in flask app
Home-page: https://github.com/arpancodes/protectsql
Author: Arpan Abhishek
Author-email: arpanforbusiness@gmail.com
License: UNKNOWN
Project-URL: Bug Tracker, https://github.com/arpancodes/protectsql/issues
Platform: UNKNOWN
License-File: LICENSE
Requires-Dist: Click
Requires-Dist: Flask
Requires-Dist: Pyre-check
